ipyscales/__init__.py
ipyscales/_example_helper.py
ipyscales/_frontend.py
ipyscales/_version.py
ipyscales/color.py
ipyscales/colorarray.py
ipyscales/colorbar.py
ipyscales/continuous.py
ipyscales/datawidgets.py
ipyscales/scale.py
ipyscales/selectors.py
ipyscales/traittypes.py
ipyscales/value.py
ipyscales/nbextension/__init__.py
ipyscales/nbextension/static/extension.js
ipyscales/nbextension/static/index.js
ipyscales/nbextension/static/index.js.LICENSE.txt
ipyscales/nbextension/static/index.js.map
ipyscales/tests/__init__.py
ipyscales/tests/conftest.py
ipyscales/tests/test_color.py
ipyscales/tests/test_colorarray.py
ipyscales/tests/test_colorbar.py
ipyscales/tests/test_continuous.py
ipyscales/tests/test_datawidgets.py
ipyscales/tests/test_nbextension_path.py
ipyscales/tests/test_selectors.py
ipyscales/tests/test_values.py
ipyscales-0.7.0.data/data/etc/jupyter/nbconfig/notebook.d/jupyter-scales.json
ipyscales-0.7.0.data/data/share/jupyter/lab/extensions/jupyter-scales-3.3.0.tgz
ipyscales-0.7.0.data/data/share/jupyter/labextensions/jupyter-scales/package.json
ipyscales-0.7.0.data/data/share/jupyter/labextensions/jupyter-scales/static/218.e9e8a5e94567e955367f.js
ipyscales-0.7.0.data/data/share/jupyter/labextensions/jupyter-scales/static/247.9b32e73f3f05407b029d.js
ipyscales-0.7.0.data/data/share/jupyter/labextensions/jupyter-scales/static/302.2f1439094ce9e6cc0976.js
ipyscales-0.7.0.data/data/share/jupyter/labextensions/jupyter-scales/static/372.080cecad96ed5ec2b330.js
ipyscales-0.7.0.data/data/share/jupyter/labextensions/jupyter-scales/static/389.4d04f1ef9aa15a575008.js
ipyscales-0.7.0.data/data/share/jupyter/labextensions/jupyter-scales/static/472.abea5071cf8b55120736.js
ipyscales-0.7.0.data/data/share/jupyter/labextensions/jupyter-scales/static/474.357167ccc91b29b2e69c.js
ipyscales-0.7.0.data/data/share/jupyter/labextensions/jupyter-scales/static/480.6c8fda73b3c5bc066d81.js
ipyscales-0.7.0.dist-info/LICENSE.txt
ipyscales-0.7.0.dist-info/METADATA
ipyscales-0.7.0.dist-info/WHEEL
ipyscales-0.7.0.dist-info/top_level.txt
ipyscales-0.7.0.dist-info/RECORD
